nbstrip_empty_cells-0.1.3.dist-info/licenses/LICENSE
remove_empty_cells/__init__.py
remove_empty_cells/cli.py
nbstrip_empty_cells-0.1.3.dist-info/METADATA
nbstrip_empty_cells-0.1.3.dist-info/WHEEL
nbstrip_empty_cells-0.1.3.dist-info/entry_points.txt
nbstrip_empty_cells-0.1.3.dist-info/top_level.txt
nbstrip_empty_cells-0.1.3.dist-info/RECORD
